{"name":"neauoire","desc":"It's always night under the ultraviolet sun.","port":["dat://0cd187bbe6a44b0462d4bc32519ee6c9a55ce25eafb3b11e33621c307e275c96/","dat://7fa4dea2b16585f994f576cc1356dc6443b8449b00fbadf70cb19827d2238fd3/","dat://00078b4ab4d6290f423686a0c77ee50bcead7a4b4f8942ea61b92be5b33bd1a9/","dat://80aef4f6f75c8df9d3b3872d71e0eb257a6ef69e38db369847203be2c0580aef/","dat://6fd46b20841eb9652081894a16014f12e19f47b97af4ab10c093284fba611d15/","dat://60f134e8fb243fbf4a0f8a252cc9aa09bdcf4ecac2efbcb8455aa01c8a04b4b0/","dat://e2a00d1a771e57eb3f1cca35d16ad112cdee94b81d83da4c4d59e1a7bed5a545/","dat://864832957014606cf35e907164f3c7670861a535e9272c6f3e063e6c7439230a/","dat://7f2ef715c36b6cd226102192ba220c73384c32e4beb49601fb3f5bba4719e0c5/","dat://ab64573efd68035014d94b83bf034012f415ff4678d3ecf291237e0bdac741b1/","dat://544e199575386e150242339a518dc33f6933ec4c8b8e82d3a7a98c095a7df026/","dat://76bcf02b4fd120d89236b58a960bcd05f5f0cb55afe9ddc0011f75ef176e52f3/"],"feed":[{"message":"This is my first post!","timestamp":1507846208609},{"message":"Now hosted on hashbase.io","timestamp":1507847924563},{"message":"experiment","timestamp":1507850815837},{"message":"hey @_discovery @deuveir!!","timestamp":1507853055644},{"message":"Testing images","timestamp":1507858912960,"media":"spike"},{"message":"hey @coston!","timestamp":1507860161635},{"message":"hey @joperron!","timestamp":1507860378450},{"message":"hey @louis","timestamp":1507861070905},{"message":"@callil yea, in the meantime you can just click on the name underneat the message.","timestamp":1507861270463},{"message":"Lol @callil, I saw that.","timestamp":1507861368442},{"message":"@louis try changing your avatar","timestamp":1507861406635},{"message":"See you in a bit! Let me know if anything breaks.","timestamp":1507861929699},{"message":"@callil I want your setup.","timestamp":1507868151103},{"message":"hey @beau! I see you :)","timestamp":1507873812919},{"message":"@louis, I think I'm starting to love the pink.","timestamp":1507875720646},{"message":"Hey @electricgecko! It's so good to see you","timestamp":1507877384655},{"message":"Good morning, I will fix up the client now. Make sure it catches the timeouts, and also make @ names clickeable by everyone.","timestamp":1507917303106},{"message":"@louis, I think I will collpase hash links too..","timestamp":1507917678622},{"message":"Testing dat://2f21e3c122ef0f2555d3a99497710cd875c7b0383f998a2d37c02c042d598485/ links collapsing","timestamp":1507919649808},{"message":"yo @inky!","timestamp":1507921196158},{"message":"hey @dom! It's good to see you, sick avatar.","timestamp":1507926354031},{"message":"@dom if your feed loads slowly, you can add feeds to your library to make them available offline and seed them other users.","timestamp":1507926425942},{"message":"In your Library, please rename your site to Rotonde(@username), so people trying to seed them know who they are actually seeding.","timestamp":1507926668929},{"message":"@dom I didn't even know you could do gradients in SVG.","timestamp":1507927042711},{"message":"@dom yup! I'm currently working on the mention tools, it should be working soon enough, and allow for others to jump in and contribute as well.","timestamp":1507927593661},{"message":"@dom find that person's feed, by clicking on their name. and paste it here, it will remove it if it's a duplicate.","timestamp":1507927912071}],"dat":"dat://2f21e3c122ef0f2555d3a99497710cd875c7b0383f998a2d37c02c042d598485/","site":"http://xxiivv.com"}